mps_watch/__init__.py
mps_watch/cli.py
mps_watch/core.py
mps_watch-0.1.2.dist-info/METADATA
mps_watch-0.1.2.dist-info/WHEEL
mps_watch-0.1.2.dist-info/entry_points.txt
mps_watch-0.1.2.dist-info/top_level.txt
mps_watch-0.1.2.dist-info/RECORD
