Metadata-Version: 2.4
Name: mps-watch
Version: 0.1.2
Summary: Apple Silicon MPS (Metal Performance Shaders) memory monitoring tool for PyTorch.
Author-email: Antigravity <antigravity@example.com>
Project-URL: Homepage, https://github.com/example/mps-watch
Classifier: Programming Language :: Python :: 3
Classifier: License :: OSI Approved :: MIT License
Classifier: Operating System :: MacOS
Requires-Python: >=3.8
Requires-Dist: torch
Requires-Dist: rich
Requires-Dist: psutil
Requires-Dist: numpy
